odoo/addons/sale_order_line_input/README.rst
odoo/addons/sale_order_line_input/__init__.py
odoo/addons/sale_order_line_input/__manifest__.py
odoo/addons/sale_order_line_input/i18n/de.po
odoo/addons/sale_order_line_input/i18n/es.po
odoo/addons/sale_order_line_input/i18n/it.po
odoo/addons/sale_order_line_input/i18n/sale_order_line_input.pot
odoo/addons/sale_order_line_input/i18n/tr.po
odoo/addons/sale_order_line_input/i18n/zh_CN.po
odoo/addons/sale_order_line_input/models/__init__.py
odoo/addons/sale_order_line_input/models/sale_order.py
odoo/addons/sale_order_line_input/readme/CONTRIBUTORS.md
odoo/addons/sale_order_line_input/readme/DESCRIPTION.md
odoo/addons/sale_order_line_input/readme/USAGE.md
odoo/addons/sale_order_line_input/static/description/icon.png
odoo/addons/sale_order_line_input/static/description/index.html
odoo/addons/sale_order_line_input/tests/__init__.py
odoo/addons/sale_order_line_input/tests/test_sale_order_line_input.py
odoo/addons/sale_order_line_input/views/sale_order_line_view.xml
odoo_addon_sale_order_line_input-18.0.1.0.0.2.dist-info/METADATA
odoo_addon_sale_order_line_input-18.0.1.0.0.2.dist-info/WHEEL
odoo_addon_sale_order_line_input-18.0.1.0.0.2.dist-info/top_level.txt
odoo_addon_sale_order_line_input-18.0.1.0.0.2.dist-info/RECORD
